{
  "tool_name": "Bash",
  "tool_input_preview": "{\"command\":\"TOKEN=\\\"fixops_ent_38wJA8mb7CsbJ3PaLvKNz7lFnLWvFWXti_5NcdISXSogi_4grP24NAe_XymVfps_\\\"\\n# Check actual available sub-paths for each broken router\\nfor base alerts sources; do\\n  code=$(curl...",
  "error": "Exit code 2\n/opt/homebrew/bin/bash: eval: line 3: syntax error near unexpected token `alerts'\n/opt/homebrew/bin/bash: eval: line 3: `for base alerts sources; do'",
  "timestamp": "2026-04-20T21:46:00.752Z",
  "retry_count": 1
}