{"nodes": [{"id": "scripts_ctem_demo_004_e2e_py", "label": "ctem_demo_004_e2e.py", "file_type": "code", "source_file": "scripts/ctem_demo_004_e2e.py", "source_location": "L1"}, {"id": "ctem_demo_004_e2e_c", "label": "C", "file_type": "code", "source_file": "scripts/ctem_demo_004_e2e.py", "source_location": "L43"}, {"id": "ctem_demo_004_e2e_results", "label": "Results", "file_type": "code", "source_file": "scripts/ctem_demo_004_e2e.py", "source_location": "L58"}, {"id": "ctem_demo_004_e2e_results_init", "label": ".__init__()", "file_type": "code", "source_file": "scripts/ctem_demo_004_e2e.py", "source_location": "L59"}, {"id": "ctem_demo_004_e2e_results_ok", "label": ".ok()", "file_type": "code", "source_file": "scripts/ctem_demo_004_e2e.py", "source_location": "L65"}, {"id": "ctem_demo_004_e2e_results_fail", "label": ".fail()", "file_type": "code", "source_file": "scripts/ctem_demo_004_e2e.py", "source_location": "L72"}, {"id": "ctem_demo_004_e2e_total", "label": "total()", "file_type": "code", "source_file": "scripts/ctem_demo_004_e2e.py", "source_location": "L80"}, {"id": "ctem_demo_004_e2e_rate", "label": "rate()", "file_type": "code", "source_file": "scripts/ctem_demo_004_e2e.py", "source_location": "L84"}, {"id": "ctem_demo_004_e2e_api", "label": "api()", "file_type": "code", "source_file": "scripts/ctem_demo_004_e2e.py", "source_location": "L90"}, {"id": "ctem_demo_004_e2e_post", "label": "post()", "file_type": "code", "source_file": "scripts/ctem_demo_004_e2e.py", "source_location": "L125"}, {"id": "ctem_demo_004_e2e_get", "label": "get()", "file_type": "code", "source_file": "scripts/ctem_demo_004_e2e.py", "source_location": "L129"}, {"id": "ctem_demo_004_e2e_upload", "label": "upload()", "file_type": "code", "source_file": "scripts/ctem_demo_004_e2e.py", "source_location": "L133"}, {"id": "ctem_demo_004_e2e_wait_for_api", "label": "wait_for_api()", "file_type": "code", "source_file": "scripts/ctem_demo_004_e2e.py", "source_location": "L177"}, {"id": "ctem_demo_004_e2e_phase_banner", "label": "phase_banner()", "file_type": "code", "source_file": "scripts/ctem_demo_004_e2e.py", "source_location": "L189"}, {"id": "ctem_demo_004_e2e_phase_1_discover", "label": "phase_1_discover()", "file_type": "code", "source_file": "scripts/ctem_demo_004_e2e.py", "source_location": "L321"}, {"id": "ctem_demo_004_e2e_phase_2_validate", "label": "phase_2_validate()", "file_type": "code", "source_file": "scripts/ctem_demo_004_e2e.py", "source_location": "L409"}, {"id": "ctem_demo_004_e2e_phase_3_remediate", "label": "phase_3_remediate()", "file_type": "code", "source_file": "scripts/ctem_demo_004_e2e.py", "source_location": "L516"}, {"id": "ctem_demo_004_e2e_phase_4_comply", "label": "phase_4_comply()", "file_type": "code", "source_file": "scripts/ctem_demo_004_e2e.py", "source_location": "L575"}, {"id": "ctem_demo_004_e2e_phase_5_measure", "label": "phase_5_measure()", "file_type": "code", "source_file": "scripts/ctem_demo_004_e2e.py", "source_location": "L629"}, {"id": "ctem_demo_004_e2e_main", "label": "main()", "file_type": "code", "source_file": "scripts/ctem_demo_004_e2e.py", "source_location": "L666"}, {"id": "ctem_demo_004_e2e_rationale_92", "label": "Make API call. Returns (status_code, data, elapsed_ms).", "file_type": "rationale", "source_file": "scripts/ctem_demo_004_e2e.py", "source_location": "L92"}, {"id": "ctem_demo_004_e2e_rationale_134", "label": "Multipart form upload.", "file_type": "rationale", "source_file": "scripts/ctem_demo_004_e2e.py", "source_location": "L134"}, {"id": "ctem_demo_004_e2e_rationale_178", "label": "Wait for API to recover after heavy operations.", "file_type": "rationale", "source_file": "scripts/ctem_demo_004_e2e.py", "source_location": "L178"}], "edges": [{"source": "scripts_ctem_demo_004_e2e_py", "target": "json", "relation": "imports", "confidence": "EXTRACTED", "source_file": "scripts/ctem_demo_004_e2e.py", "source_location": "L22", "weight": 1.0}, {"source": "scripts_ctem_demo_004_e2e_py", "target": "os", "relation": "imports", "confidence": "EXTRACTED", "source_file": "scripts/ctem_demo_004_e2e.py", "source_location": "L23", "weight": 1.0}, {"source": "scripts_ctem_demo_004_e2e_py", "target": "sys", "relation": "imports", "confidence": "EXTRACTED", "source_file": "scripts/ctem_demo_004_e2e.py", "source_location": "L24", "weight": 1.0}, {"source": "scripts_ctem_demo_004_e2e_py", "target": "time", "relation": "imports", "confidence": "EXTRACTED", "source_file": "scripts/ctem_demo_004_e2e.py", "source_location": "L25", "weight": 1.0}, {"source": "scripts_ctem_demo_004_e2e_py", "target": "tempfile", "relation": "imports", "confidence": "EXTRACTED", "source_file": "scripts/ctem_demo_004_e2e.py", "source_location": "L26", "weight": 1.0}, {"source": "scripts_ctem_demo_004_e2e_py", "target": "urllib_request", "relation": "imports", "confidence": "EXTRACTED", "source_file": "scripts/ctem_demo_004_e2e.py", "source_location": "L27", "weight": 1.0}, {"source": "scripts_ctem_demo_004_e2e_py", "target": "urllib_error", "relation": "imports", "confidence": "EXTRACTED", "source_file": "scripts/ctem_demo_004_e2e.py", "source_location": "L28", "weight": 1.0}, {"source": "scripts_ctem_demo_004_e2e_py", "target": "datetime", "relation": "imports_from", "confidence": "EXTRACTED", "source_file": "scripts/ctem_demo_004_e2e.py", "source_location": "L29", "weight": 1.0}, {"source": "scripts_ctem_demo_004_e2e_py", "target": "typing", "relation": "imports_from", "confidence": "EXTRACTED", "source_file": "scripts/ctem_demo_004_e2e.py", "source_location": "L30", "weight": 1.0}, {"source": "scripts_ctem_demo_004_e2e_py", "target": "ctem_demo_004_e2e_c", "relation": "contains", "confidence": "EXTRACTED", "source_file": "scripts/ctem_demo_004_e2e.py", "source_location": "L43", "weight": 1.0}, {"source": "scripts_ctem_demo_004_e2e_py", "target": "ctem_demo_004_e2e_results", "relation": "contains", "confidence": "EXTRACTED", "source_file": "scripts/ctem_demo_004_e2e.py", "source_location": "L58", "weight": 1.0}, {"source": "ctem_demo_004_e2e_results", "target": "ctem_demo_004_e2e_results_init", "relation": "method", "confidence": "EXTRACTED", "source_file": "scripts/ctem_demo_004_e2e.py", "source_location": "L59", "weight": 1.0}, {"source": "ctem_demo_004_e2e_results", "target": "ctem_demo_004_e2e_results_ok", "relation": "method", "confidence": "EXTRACTED", "source_file": "scripts/ctem_demo_004_e2e.py", "source_location": "L65", "weight": 1.0}, {"source": "ctem_demo_004_e2e_results", "target": "ctem_demo_004_e2e_results_fail", "relation": "method", "confidence": "EXTRACTED", "source_file": "scripts/ctem_demo_004_e2e.py", "source_location": "L72", "weight": 1.0}, {"source": "scripts_ctem_demo_004_e2e_py", "target": "ctem_demo_004_e2e_total", "relation": "contains", "confidence": "EXTRACTED", "source_file": "scripts/ctem_demo_004_e2e.py", "source_location": "L80", "weight": 1.0}, {"source": "scripts_ctem_demo_004_e2e_py", "target": "ctem_demo_004_e2e_rate", "relation": "contains", "confidence": "EXTRACTED", "source_file": "scripts/ctem_demo_004_e2e.py", "source_location": "L84", "weight": 1.0}, {"source": "scripts_ctem_demo_004_e2e_py", "target": "ctem_demo_004_e2e_api", "relation": "contains", "confidence": "EXTRACTED", "source_file": "scripts/ctem_demo_004_e2e.py", "source_location": "L90", "weight": 1.0}, {"source": "scripts_ctem_demo_004_e2e_py", "target": "ctem_demo_004_e2e_post", "relation": "contains", "confidence": "EXTRACTED", "source_file": "scripts/ctem_demo_004_e2e.py", "source_location": "L125", "weight": 1.0}, {"source": "scripts_ctem_demo_004_e2e_py", "target": "ctem_demo_004_e2e_get", "relation": "contains", "confidence": "EXTRACTED", "source_file": "scripts/ctem_demo_004_e2e.py", "source_location": "L129", "weight": 1.0}, {"source": "scripts_ctem_demo_004_e2e_py", "target": "ctem_demo_004_e2e_upload", "relation": "contains", "confidence": "EXTRACTED", "source_file": "scripts/ctem_demo_004_e2e.py", "source_location": "L133", "weight": 1.0}, {"source": "scripts_ctem_demo_004_e2e_py", "target": "ctem_demo_004_e2e_wait_for_api", "relation": "contains", "confidence": "EXTRACTED", "source_file": "scripts/ctem_demo_004_e2e.py", "source_location": "L177", "weight": 1.0}, {"source": "scripts_ctem_demo_004_e2e_py", "target": "ctem_demo_004_e2e_phase_banner", "relation": "contains", "confidence": "EXTRACTED", "source_file": "scripts/ctem_demo_004_e2e.py", "source_location": "L189", "weight": 1.0}, {"source": "scripts_ctem_demo_004_e2e_py", "target": "ctem_demo_004_e2e_phase_1_discover", "relation": "contains", "confidence": "EXTRACTED", "source_file": "scripts/ctem_demo_004_e2e.py", "source_location": "L321", "weight": 1.0}, {"source": "scripts_ctem_demo_004_e2e_py", "target": "ctem_demo_004_e2e_phase_2_validate", "relation": "contains", "confidence": "EXTRACTED", "source_file": "scripts/ctem_demo_004_e2e.py", "source_location": "L409", "weight": 1.0}, {"source": "scripts_ctem_demo_004_e2e_py", "target": "ctem_demo_004_e2e_phase_3_remediate", "relation": "contains", "confidence": "EXTRACTED", "source_file": "scripts/ctem_demo_004_e2e.py", "source_location": "L516", "weight": 1.0}, {"source": "scripts_ctem_demo_004_e2e_py", "target": "ctem_demo_004_e2e_phase_4_comply", "relation": "contains", "confidence": "EXTRACTED", "source_file": "scripts/ctem_demo_004_e2e.py", "source_location": "L575", "weight": 1.0}, {"source": "scripts_ctem_demo_004_e2e_py", "target": "ctem_demo_004_e2e_phase_5_measure", "relation": "contains", "confidence": "EXTRACTED", "source_file": "scripts/ctem_demo_004_e2e.py", "source_location": "L629", "weight": 1.0}, {"source": "scripts_ctem_demo_004_e2e_py", "target": "ctem_demo_004_e2e_main", "relation": "contains", "confidence": "EXTRACTED", "source_file": "scripts/ctem_demo_004_e2e.py", "source_location": "L666", "weight": 1.0}, {"source": "ctem_demo_004_e2e_post", "target": "ctem_demo_004_e2e_api", "relation": "calls", "confidence": "EXTRACTED", "source_file": "scripts/ctem_demo_004_e2e.py", "source_location": "L126", "weight": 1.0}, {"source": "ctem_demo_004_e2e_get", "target": "ctem_demo_004_e2e_api", "relation": "calls", "confidence": "EXTRACTED", "source_file": "scripts/ctem_demo_004_e2e.py", "source_location": "L130", "weight": 1.0}, {"source": "ctem_demo_004_e2e_wait_for_api", "target": "ctem_demo_004_e2e_get", "relation": "calls", "confidence": "EXTRACTED", "source_file": "scripts/ctem_demo_004_e2e.py", "source_location": "L181", "weight": 1.0}, {"source": "ctem_demo_004_e2e_phase_1_discover", "target": "ctem_demo_004_e2e_phase_banner", "relation": "calls", "confidence": "EXTRACTED", "source_file": "scripts/ctem_demo_004_e2e.py", "source_location": "L322", "weight": 1.0}, {"source": "ctem_demo_004_e2e_phase_1_discover", "target": "ctem_demo_004_e2e_post", "relation": "calls", "confidence": "EXTRACTED", "source_file": "scripts/ctem_demo_004_e2e.py", "source_location": "L326", "weight": 1.0}, {"source": "ctem_demo_004_e2e_phase_1_discover", "target": "ctem_demo_004_e2e_get", "relation": "calls", "confidence": "EXTRACTED", "source_file": "scripts/ctem_demo_004_e2e.py", "source_location": "L330", "weight": 1.0}, {"source": "ctem_demo_004_e2e_phase_1_discover", "target": "ctem_demo_004_e2e_results_ok", "relation": "calls", "confidence": "EXTRACTED", "source_file": "scripts/ctem_demo_004_e2e.py", "source_location": "L332", "weight": 1.0}, {"source": "ctem_demo_004_e2e_phase_1_discover", "target": "ctem_demo_004_e2e_results_fail", "relation": "calls", "confidence": "EXTRACTED", "source_file": "scripts/ctem_demo_004_e2e.py", "source_location": "L334", "weight": 1.0}, {"source": "ctem_demo_004_e2e_phase_1_discover", "target": "ctem_demo_004_e2e_upload", "relation": "calls", "confidence": "EXTRACTED", "source_file": "scripts/ctem_demo_004_e2e.py", "source_location": "L373", "weight": 1.0}, {"source": "ctem_demo_004_e2e_phase_2_validate", "target": "ctem_demo_004_e2e_phase_banner", "relation": "calls", "confidence": "EXTRACTED", "source_file": "scripts/ctem_demo_004_e2e.py", "source_location": "L410", "weight": 1.0}, {"source": "ctem_demo_004_e2e_phase_2_validate", "target": "ctem_demo_004_e2e_post", "relation": "calls", "confidence": "EXTRACTED", "source_file": "scripts/ctem_demo_004_e2e.py", "source_location": "L413", "weight": 1.0}, {"source": "ctem_demo_004_e2e_phase_2_validate", "target": "ctem_demo_004_e2e_get", "relation": "calls", "confidence": "EXTRACTED", "source_file": "scripts/ctem_demo_004_e2e.py", "source_location": "L421", "weight": 1.0}, {"source": "ctem_demo_004_e2e_phase_2_validate", "target": "ctem_demo_004_e2e_results_ok", "relation": "calls", "confidence": "EXTRACTED", "source_file": "scripts/ctem_demo_004_e2e.py", "source_location": "L429", "weight": 1.0}, {"source": "ctem_demo_004_e2e_phase_2_validate", "target": "ctem_demo_004_e2e_results_fail", "relation": "calls", "confidence": "EXTRACTED", "source_file": "scripts/ctem_demo_004_e2e.py", "source_location": "L435", "weight": 1.0}, {"source": "ctem_demo_004_e2e_phase_2_validate", "target": "ctem_demo_004_e2e_wait_for_api", "relation": "calls", "confidence": "EXTRACTED", "source_file": "scripts/ctem_demo_004_e2e.py", "source_location": "L437", "weight": 1.0}, {"source": "ctem_demo_004_e2e_phase_3_remediate", "target": "ctem_demo_004_e2e_phase_banner", "relation": "calls", "confidence": "EXTRACTED", "source_file": "scripts/ctem_demo_004_e2e.py", "source_location": "L517", "weight": 1.0}, {"source": "ctem_demo_004_e2e_phase_3_remediate", "target": "ctem_demo_004_e2e_post", "relation": "calls", "confidence": "EXTRACTED", "source_file": "scripts/ctem_demo_004_e2e.py", "source_location": "L520", "weight": 1.0}, {"source": "ctem_demo_004_e2e_phase_3_remediate", "target": "ctem_demo_004_e2e_get", "relation": "calls", "confidence": "EXTRACTED", "source_file": "scripts/ctem_demo_004_e2e.py", "source_location": "L536", "weight": 1.0}, {"source": "ctem_demo_004_e2e_phase_3_remediate", "target": "ctem_demo_004_e2e_results_ok", "relation": "calls", "confidence": "EXTRACTED", "source_file": "scripts/ctem_demo_004_e2e.py", "source_location": "L540", "weight": 1.0}, {"source": "ctem_demo_004_e2e_phase_3_remediate", "target": "ctem_demo_004_e2e_results_fail", "relation": "calls", "confidence": "EXTRACTED", "source_file": "scripts/ctem_demo_004_e2e.py", "source_location": "L546", "weight": 1.0}, {"source": "ctem_demo_004_e2e_phase_4_comply", "target": "ctem_demo_004_e2e_phase_banner", "relation": "calls", "confidence": "EXTRACTED", "source_file": "scripts/ctem_demo_004_e2e.py", "source_location": "L576", "weight": 1.0}, {"source": "ctem_demo_004_e2e_phase_4_comply", "target": "ctem_demo_004_e2e_post", "relation": "calls", "confidence": "EXTRACTED", "source_file": "scripts/ctem_demo_004_e2e.py", "source_location": "L581", "weight": 1.0}, {"source": "ctem_demo_004_e2e_phase_4_comply", "target": "ctem_demo_004_e2e_get", "relation": "calls", "confidence": "EXTRACTED", "source_file": "scripts/ctem_demo_004_e2e.py", "source_location": "L586", "weight": 1.0}, {"source": "ctem_demo_004_e2e_phase_4_comply", "target": "ctem_demo_004_e2e_results_ok", "relation": "calls", "confidence": "EXTRACTED", "source_file": "scripts/ctem_demo_004_e2e.py", "source_location": "L587", "weight": 1.0}, {"source": "ctem_demo_004_e2e_phase_4_comply", "target": "ctem_demo_004_e2e_results_fail", "relation": "calls", "confidence": "EXTRACTED", "source_file": "scripts/ctem_demo_004_e2e.py", "source_location": "L589", "weight": 1.0}, {"source": "ctem_demo_004_e2e_phase_5_measure", "target": "ctem_demo_004_e2e_phase_banner", "relation": "calls", "confidence": "EXTRACTED", "source_file": "scripts/ctem_demo_004_e2e.py", "source_location": "L630", "weight": 1.0}, {"source": "ctem_demo_004_e2e_phase_5_measure", "target": "ctem_demo_004_e2e_get", "relation": "calls", "confidence": "EXTRACTED", "source_file": "scripts/ctem_demo_004_e2e.py", "source_location": "L633", "weight": 1.0}, {"source": "ctem_demo_004_e2e_phase_5_measure", "target": "ctem_demo_004_e2e_results_ok", "relation": "calls", "confidence": "EXTRACTED", "source_file": "scripts/ctem_demo_004_e2e.py", "source_location": "L635", "weight": 1.0}, {"source": "ctem_demo_004_e2e_phase_5_measure", "target": "ctem_demo_004_e2e_results_fail", "relation": "calls", "confidence": "EXTRACTED", "source_file": "scripts/ctem_demo_004_e2e.py", "source_location": "L637", "weight": 1.0}, {"source": "ctem_demo_004_e2e_phase_5_measure", "target": "ctem_demo_004_e2e_post", "relation": "calls", "confidence": "EXTRACTED", "source_file": "scripts/ctem_demo_004_e2e.py", "source_location": "L640", "weight": 1.0}, {"source": "ctem_demo_004_e2e_main", "target": "ctem_demo_004_e2e_get", "relation": "calls", "confidence": "EXTRACTED", "source_file": "scripts/ctem_demo_004_e2e.py", "source_location": "L678", "weight": 1.0}, {"source": "ctem_demo_004_e2e_main", "target": "ctem_demo_004_e2e_phase_1_discover", "relation": "calls", "confidence": "EXTRACTED", "source_file": "scripts/ctem_demo_004_e2e.py", "source_location": "L686", "weight": 1.0}, {"source": "ctem_demo_004_e2e_main", "target": "ctem_demo_004_e2e_phase_2_validate", "relation": "calls", "confidence": "EXTRACTED", "source_file": "scripts/ctem_demo_004_e2e.py", "source_location": "L687", "weight": 1.0}, {"source": "ctem_demo_004_e2e_main", "target": "ctem_demo_004_e2e_phase_3_remediate", "relation": "calls", "confidence": "EXTRACTED", "source_file": "scripts/ctem_demo_004_e2e.py", "source_location": "L688", "weight": 1.0}, {"source": "ctem_demo_004_e2e_main", "target": "ctem_demo_004_e2e_phase_4_comply", "relation": "calls", "confidence": "EXTRACTED", "source_file": "scripts/ctem_demo_004_e2e.py", "source_location": "L689", "weight": 1.0}, {"source": "ctem_demo_004_e2e_main", "target": "ctem_demo_004_e2e_phase_5_measure", "relation": "calls", "confidence": "EXTRACTED", "source_file": "scripts/ctem_demo_004_e2e.py", "source_location": "L690", "weight": 1.0}, {"source": "ctem_demo_004_e2e_rationale_92", "target": "ctem_demo_004_e2e_api", "relation": "rationale_for", "confidence": "EXTRACTED", "source_file": "scripts/ctem_demo_004_e2e.py", "source_location": "L92", "weight": 1.0}, {"source": "ctem_demo_004_e2e_rationale_134", "target": "ctem_demo_004_e2e_upload", "relation": "rationale_for", "confidence": "EXTRACTED", "source_file": "scripts/ctem_demo_004_e2e.py", "source_location": "L134", "weight": 1.0}, {"source": "ctem_demo_004_e2e_rationale_178", "target": "ctem_demo_004_e2e_wait_for_api", "relation": "rationale_for", "confidence": "EXTRACTED", "source_file": "scripts/ctem_demo_004_e2e.py", "source_location": "L178", "weight": 1.0}], "raw_calls": [{"caller_nid": "ctem_demo_004_e2e_results_ok", "callee": "append", "source_file": "scripts/ctem_demo_004_e2e.py", "source_location": "L67"}, {"caller_nid": "ctem_demo_004_e2e_results_ok", "callee": "print", "source_file": "scripts/ctem_demo_004_e2e.py", "source_location": "L70"}, {"caller_nid": "ctem_demo_004_e2e_results_fail", "callee": "append", "source_file": "scripts/ctem_demo_004_e2e.py", "source_location": "L74"}, {"caller_nid": "ctem_demo_004_e2e_results_fail", "callee": "print", "source_file": "scripts/ctem_demo_004_e2e.py", "source_location": "L77"}, {"caller_nid": "ctem_demo_004_e2e_api", "callee": "lstrip", "source_file": "scripts/ctem_demo_004_e2e.py", "source_location": "L93"}, {"caller_nid": "ctem_demo_004_e2e_api", "callee": "encode", "source_file": "scripts/ctem_demo_004_e2e.py", "source_location": "L94"}, {"caller_nid": "ctem_demo_004_e2e_api", "callee": "dumps", "source_file": "scripts/ctem_demo_004_e2e.py", "source_location": "L94"}, {"caller_nid": "ctem_demo_004_e2e_api", "callee": "copy", "source_file": "scripts/ctem_demo_004_e2e.py", "source_location": "L95"}, {"caller_nid": "ctem_demo_004_e2e_api", "callee": "Request", "source_file": "scripts/ctem_demo_004_e2e.py", "source_location": "L96"}, {"caller_nid": "ctem_demo_004_e2e_api", "callee": "range", "source_file": "scripts/ctem_demo_004_e2e.py", "source_location": "L98"}, {"caller_nid": "ctem_demo_004_e2e_api", "callee": "time", "source_file": "scripts/ctem_demo_004_e2e.py", "source_location": "L99"}, {"caller_nid": "ctem_demo_004_e2e_api", "callee": "urlopen", "source_file": "scripts/ctem_demo_004_e2e.py", "source_location": "L101"}, {"caller_nid": "ctem_demo_004_e2e_api", "callee": "decode", "source_file": "scripts/ctem_demo_004_e2e.py", "source_location": "L102"}, {"caller_nid": "ctem_demo_004_e2e_api", "callee": "read", "source_file": "scripts/ctem_demo_004_e2e.py", "source_location": "L102"}, {"caller_nid": "ctem_demo_004_e2e_api", "callee": "int", "source_file": "scripts/ctem_demo_004_e2e.py", "source_location": "L103"}, {"caller_nid": "ctem_demo_004_e2e_api", "callee": "time", "source_file": "scripts/ctem_demo_004_e2e.py", "source_location": "L103"}, {"caller_nid": "ctem_demo_004_e2e_api", "callee": "getcode", "source_file": "scripts/ctem_demo_004_e2e.py", "source_location": "L105"}, {"caller_nid": "ctem_demo_004_e2e_api", "callee": "loads", "source_file": "scripts/ctem_demo_004_e2e.py", "source_location": "L105"}, {"caller_nid": "ctem_demo_004_e2e_api", "callee": "getcode", "source_file": "scripts/ctem_demo_004_e2e.py", "source_location": "L107"}, {"caller_nid": "ctem_demo_004_e2e_api", "callee": "int", "source_file": "scripts/ctem_demo_004_e2e.py", "source_location": "L109"}, {"caller_nid": "ctem_demo_004_e2e_api", "callee": "time", "source_file": "scripts/ctem_demo_004_e2e.py", "source_location": "L109"}, {"caller_nid": "ctem_demo_004_e2e_api", "callee": "decode", "source_file": "scripts/ctem_demo_004_e2e.py", "source_location": "L110"}, {"caller_nid": "ctem_demo_004_e2e_api", "callee": "read", "source_file": "scripts/ctem_demo_004_e2e.py", "source_location": "L110"}, {"caller_nid": "ctem_demo_004_e2e_api", "callee": "loads", "source_file": "scripts/ctem_demo_004_e2e.py", "source_location": "L112"}, {"caller_nid": "ctem_demo_004_e2e_api", "callee": "int", "source_file": "scripts/ctem_demo_004_e2e.py", "source_location": "L116"}, {"caller_nid": "ctem_demo_004_e2e_api", "callee": "time", "source_file": "scripts/ctem_demo_004_e2e.py", "source_location": "L116"}, {"caller_nid": "ctem_demo_004_e2e_api", "callee": "sleep", "source_file": "scripts/ctem_demo_004_e2e.py", "source_location": "L118"}, {"caller_nid": "ctem_demo_004_e2e_api", "callee": "str", "source_file": "scripts/ctem_demo_004_e2e.py", "source_location": "L120"}, {"caller_nid": "ctem_demo_004_e2e_upload", "callee": "open", "source_file": "scripts/ctem_demo_004_e2e.py", "source_location": "L136"}, {"caller_nid": "ctem_demo_004_e2e_upload", "callee": "read", "source_file": "scripts/ctem_demo_004_e2e.py", "source_location": "L137"}, {"caller_nid": "ctem_demo_004_e2e_upload", "callee": "basename", "source_file": "scripts/ctem_demo_004_e2e.py", "source_location": "L138"}, {"caller_nid": "ctem_demo_004_e2e_upload", "callee": "append", "source_file": "scripts/ctem_demo_004_e2e.py", "source_location": "L141"}, {"caller_nid": "ctem_demo_004_e2e_upload", "callee": "encode", "source_file": "scripts/ctem_demo_004_e2e.py", "source_location": "L141"}, {"caller_nid": "ctem_demo_004_e2e_upload", "callee": "append", "source_file": "scripts/ctem_demo_004_e2e.py", "source_location": "L142"}, {"caller_nid": "ctem_demo_004_e2e_upload", "callee": "encode", "source_file": "scripts/ctem_demo_004_e2e.py", "source_location": "L143"}, {"caller_nid": "ctem_demo_004_e2e_upload", "callee": "append", "source_file": "scripts/ctem_demo_004_e2e.py", "source_location": "L145"}, {"caller_nid": "ctem_demo_004_e2e_upload", "callee": "encode", "source_file": "scripts/ctem_demo_004_e2e.py", "source_location": "L145"}, {"caller_nid": "ctem_demo_004_e2e_upload", "callee": "append", "source_file": "scripts/ctem_demo_004_e2e.py", "source_location": "L146"}, {"caller_nid": "ctem_demo_004_e2e_upload", "callee": "append", "source_file": "scripts/ctem_demo_004_e2e.py", "source_location": "L147"}, {"caller_nid": "ctem_demo_004_e2e_upload", "callee": "append", "source_file": "scripts/ctem_demo_004_e2e.py", "source_location": "L148"}, {"caller_nid": "ctem_demo_004_e2e_upload", "callee": "encode", "source_file": "scripts/ctem_demo_004_e2e.py", "source_location": "L148"}, {"caller_nid": "ctem_demo_004_e2e_upload", "callee": "join", "source_file": "scripts/ctem_demo_004_e2e.py", "source_location": "L149"}, {"caller_nid": "ctem_demo_004_e2e_upload", "callee": "lstrip", "source_file": "scripts/ctem_demo_004_e2e.py", "source_location": "L151"}, {"caller_nid": "ctem_demo_004_e2e_upload", "callee": "Request", "source_file": "scripts/ctem_demo_004_e2e.py", "source_location": "L152"}, {"caller_nid": "ctem_demo_004_e2e_upload", "callee": "add_header", "source_file": "scripts/ctem_demo_004_e2e.py", "source_location": "L153"}, {"caller_nid": "ctem_demo_004_e2e_upload", "callee": "add_header", "source_file": "scripts/ctem_demo_004_e2e.py", "source_location": "L154"}, {"caller_nid": "ctem_demo_004_e2e_upload", "callee": "time", "source_file": "scripts/ctem_demo_004_e2e.py", "source_location": "L156"}, {"caller_nid": "ctem_demo_004_e2e_upload", "callee": "urlopen", "source_file": "scripts/ctem_demo_004_e2e.py", "source_location": "L158"}, {"caller_nid": "ctem_demo_004_e2e_upload", "callee": "int", "source_file": "scripts/ctem_demo_004_e2e.py", "source_location": "L159"}, {"caller_nid": "ctem_demo_004_e2e_upload", "callee": "time", "source_file": "scripts/ctem_demo_004_e2e.py", "source_location": "L159"}, {"caller_nid": "ctem_demo_004_e2e_upload", "callee": "decode", "source_file": "scripts/ctem_demo_004_e2e.py", "source_location": "L160"}, {"caller_nid": "ctem_demo_004_e2e_upload", "callee": "read", "source_file": "scripts/ctem_demo_004_e2e.py", "source_location": "L160"}, {"caller_nid": "ctem_demo_004_e2e_upload", "callee": "getcode", "source_file": "scripts/ctem_demo_004_e2e.py", "source_location": "L162"}, {"caller_nid": "ctem_demo_004_e2e_upload", "callee": "loads", "source_file": "scripts/ctem_demo_004_e2e.py", "source_location": "L162"}, {"caller_nid": "ctem_demo_004_e2e_upload", "callee": "getcode", "source_file": "scripts/ctem_demo_004_e2e.py", "source_location": "L164"}, {"caller_nid": "ctem_demo_004_e2e_upload", "callee": "int", "source_file": "scripts/ctem_demo_004_e2e.py", "source_location": "L166"}, {"caller_nid": "ctem_demo_004_e2e_upload", "callee": "time", "source_file": "scripts/ctem_demo_004_e2e.py", "source_location": "L166"}, {"caller_nid": "ctem_demo_004_e2e_upload", "callee": "decode", "source_file": "scripts/ctem_demo_004_e2e.py", "source_location": "L167"}, {"caller_nid": "ctem_demo_004_e2e_upload", "callee": "read", "source_file": "scripts/ctem_demo_004_e2e.py", "source_location": "L167"}, {"caller_nid": "ctem_demo_004_e2e_upload", "callee": "loads", "source_file": "scripts/ctem_demo_004_e2e.py", "source_location": "L169"}, {"caller_nid": "ctem_demo_004_e2e_upload", "callee": "int", "source_file": "scripts/ctem_demo_004_e2e.py", "source_location": "L173"}, {"caller_nid": "ctem_demo_004_e2e_upload", "callee": "time", "source_file": "scripts/ctem_demo_004_e2e.py", "source_location": "L173"}, {"caller_nid": "ctem_demo_004_e2e_upload", "callee": "str", "source_file": "scripts/ctem_demo_004_e2e.py", "source_location": "L174"}, {"caller_nid": "ctem_demo_004_e2e_wait_for_api", "callee": "range", "source_file": "scripts/ctem_demo_004_e2e.py", "source_location": "L179"}, {"caller_nid": "ctem_demo_004_e2e_wait_for_api", "callee": "sleep", "source_file": "scripts/ctem_demo_004_e2e.py", "source_location": "L186"}, {"caller_nid": "ctem_demo_004_e2e_phase_banner", "callee": "print", "source_file": "scripts/ctem_demo_004_e2e.py", "source_location": "L192"}, {"caller_nid": "ctem_demo_004_e2e_phase_1_discover", "callee": "isinstance", "source_file": "scripts/ctem_demo_004_e2e.py", "source_location": "L329"}, {"caller_nid": "ctem_demo_004_e2e_phase_1_discover", "callee": "len", "source_file": "scripts/ctem_demo_004_e2e.py", "source_location": "L330"}, {"caller_nid": "ctem_demo_004_e2e_phase_1_discover", "callee": "len", "source_file": "scripts/ctem_demo_004_e2e.py", "source_location": "L341"}, {"caller_nid": "ctem_demo_004_e2e_phase_1_discover", "callee": "len", "source_file": "scripts/ctem_demo_004_e2e.py", "source_location": "L352"}, {"caller_nid": "ctem_demo_004_e2e_phase_1_discover", "callee": "len", "source_file": "scripts/ctem_demo_004_e2e.py", "source_location": "L363"}, {"caller_nid": "ctem_demo_004_e2e_phase_1_discover", "callee": "NamedTemporaryFile", "source_file": "scripts/ctem_demo_004_e2e.py", "source_location": "L370"}, {"caller_nid": "ctem_demo_004_e2e_phase_1_discover", "callee": "dump", "source_file": "scripts/ctem_demo_004_e2e.py", "source_location": "L371"}, {"caller_nid": "ctem_demo_004_e2e_phase_1_discover", "callee": "unlink", "source_file": "scripts/ctem_demo_004_e2e.py", "source_location": "L374"}, {"caller_nid": "ctem_demo_004_e2e_phase_1_discover", "callee": "len", "source_file": "scripts/ctem_demo_004_e2e.py", "source_location": "L376"}, {"caller_nid": "ctem_demo_004_e2e_phase_1_discover", "callee": "NamedTemporaryFile", "source_file": "scripts/ctem_demo_004_e2e.py", "source_location": "L381"}, {"caller_nid": "ctem_demo_004_e2e_phase_1_discover", "callee": "dump", "source_file": "scripts/ctem_demo_004_e2e.py", "source_location": "L382"}, {"caller_nid": "ctem_demo_004_e2e_phase_1_discover", "callee": "unlink", "source_file": "scripts/ctem_demo_004_e2e.py", "source_location": "L385"}, {"caller_nid": "ctem_demo_004_e2e_phase_1_discover", "callee": "len", "source_file": "scripts/ctem_demo_004_e2e.py", "source_location": "L387"}, {"caller_nid": "ctem_demo_004_e2e_phase_1_discover", "callee": "NamedTemporaryFile", "source_file": "scripts/ctem_demo_004_e2e.py", "source_location": "L392"}, {"caller_nid": "ctem_demo_004_e2e_phase_1_discover", "callee": "dump", "source_file": "scripts/ctem_demo_004_e2e.py", "source_location": "L393"}, {"caller_nid": "ctem_demo_004_e2e_phase_1_discover", "callee": "unlink", "source_file": "scripts/ctem_demo_004_e2e.py", "source_location": "L396"}, {"caller_nid": "ctem_demo_004_e2e_phase_1_discover", "callee": "len", "source_file": "scripts/ctem_demo_004_e2e.py", "source_location": "L398"}, {"caller_nid": "ctem_demo_004_e2e_phase_2_validate", "callee": "isinstance", "source_file": "scripts/ctem_demo_004_e2e.py", "source_location": "L420"}, {"caller_nid": "ctem_demo_004_e2e_phase_2_validate", "callee": "len", "source_file": "scripts/ctem_demo_004_e2e.py", "source_location": "L430"}, {"caller_nid": "ctem_demo_004_e2e_phase_2_validate", "callee": "isinstance", "source_file": "scripts/ctem_demo_004_e2e.py", "source_location": "L445"}, {"caller_nid": "ctem_demo_004_e2e_phase_2_validate", "callee": "isinstance", "source_file": "scripts/ctem_demo_004_e2e.py", "source_location": "L459"}, {"caller_nid": "ctem_demo_004_e2e_phase_2_validate", "callee": "isinstance", "source_file": "scripts/ctem_demo_004_e2e.py", "source_location": "L465"}, {"caller_nid": "ctem_demo_004_e2e_phase_2_validate", "callee": "isinstance", "source_file": "scripts/ctem_demo_004_e2e.py", "source_location": "L489"}, {"caller_nid": "ctem_demo_004_e2e_phase_3_remediate", "callee": "isinstance", "source_file": "scripts/ctem_demo_004_e2e.py", "source_location": "L535"}, {"caller_nid": "ctem_demo_004_e2e_phase_3_remediate", "callee": "isinstance", "source_file": "scripts/ctem_demo_004_e2e.py", "source_location": "L556"}, {"caller_nid": "ctem_demo_004_e2e_phase_3_remediate", "callee": "len", "source_file": "scripts/ctem_demo_004_e2e.py", "source_location": "L558"}, {"caller_nid": "ctem_demo_004_e2e_phase_4_comply", "callee": "isinstance", "source_file": "scripts/ctem_demo_004_e2e.py", "source_location": "L585"}, {"caller_nid": "ctem_demo_004_e2e_phase_4_comply", "callee": "isinstance", "source_file": "scripts/ctem_demo_004_e2e.py", "source_location": "L604"}, {"caller_nid": "ctem_demo_004_e2e_phase_4_comply", "callee": "isinstance", "source_file": "scripts/ctem_demo_004_e2e.py", "source_location": "L615"}, {"caller_nid": "ctem_demo_004_e2e_phase_5_measure", "callee": "isinstance", "source_file": "scripts/ctem_demo_004_e2e.py", "source_location": "L645"}, {"caller_nid": "ctem_demo_004_e2e_phase_5_measure", "callee": "len", "source_file": "scripts/ctem_demo_004_e2e.py", "source_location": "L657"}, {"caller_nid": "ctem_demo_004_e2e_phase_5_measure", "callee": "len", "source_file": "scripts/ctem_demo_004_e2e.py", "source_location": "L658"}, {"caller_nid": "ctem_demo_004_e2e_phase_5_measure", "callee": "len", "source_file": "scripts/ctem_demo_004_e2e.py", "source_location": "L660"}, {"caller_nid": "ctem_demo_004_e2e_main", "callee": "time", "source_file": "scripts/ctem_demo_004_e2e.py", "source_location": "L667"}, {"caller_nid": "ctem_demo_004_e2e_main", "callee": "print", "source_file": "scripts/ctem_demo_004_e2e.py", "source_location": "L670"}, {"caller_nid": "ctem_demo_004_e2e_main", "callee": "print", "source_file": "scripts/ctem_demo_004_e2e.py", "source_location": "L671"}, {"caller_nid": "ctem_demo_004_e2e_main", "callee": "print", "source_file": "scripts/ctem_demo_004_e2e.py", "source_location": "L672"}, {"caller_nid": "ctem_demo_004_e2e_main", "callee": "print", "source_file": "scripts/ctem_demo_004_e2e.py", "source_location": "L673"}, {"caller_nid": "ctem_demo_004_e2e_main", "callee": "print", "source_file": "scripts/ctem_demo_004_e2e.py", "source_location": "L674"}, {"caller_nid": "ctem_demo_004_e2e_main", "callee": "print", "source_file": "scripts/ctem_demo_004_e2e.py", "source_location": "L675"}, {"caller_nid": "ctem_demo_004_e2e_main", "callee": "print", "source_file": "scripts/ctem_demo_004_e2e.py", "source_location": "L680"}, {"caller_nid": "ctem_demo_004_e2e_main", "callee": "exit", "source_file": "scripts/ctem_demo_004_e2e.py", "source_location": "L681"}, {"caller_nid": "ctem_demo_004_e2e_main", "callee": "print", "source_file": "scripts/ctem_demo_004_e2e.py", "source_location": "L683"}, {"caller_nid": "ctem_demo_004_e2e_main", "callee": "int", "source_file": "scripts/ctem_demo_004_e2e.py", "source_location": "L692"}, {"caller_nid": "ctem_demo_004_e2e_main", "callee": "time", "source_file": "scripts/ctem_demo_004_e2e.py", "source_location": "L692"}, {"caller_nid": "ctem_demo_004_e2e_main", "callee": "isoformat", "source_file": "scripts/ctem_demo_004_e2e.py", "source_location": "L697"}, {"caller_nid": "ctem_demo_004_e2e_main", "callee": "now", "source_file": "scripts/ctem_demo_004_e2e.py", "source_location": "L697"}, {"caller_nid": "ctem_demo_004_e2e_main", "callee": "round", "source_file": "scripts/ctem_demo_004_e2e.py", "source_location": "L701"}, {"caller_nid": "ctem_demo_004_e2e_main", "callee": "print", "source_file": "scripts/ctem_demo_004_e2e.py", "source_location": "L706"}, {"caller_nid": "ctem_demo_004_e2e_main", "callee": "dumps", "source_file": "scripts/ctem_demo_004_e2e.py", "source_location": "L706"}, {"caller_nid": "ctem_demo_004_e2e_main", "callee": "print", "source_file": "scripts/ctem_demo_004_e2e.py", "source_location": "L708"}, {"caller_nid": "ctem_demo_004_e2e_main", "callee": "print", "source_file": "scripts/ctem_demo_004_e2e.py", "source_location": "L710"}, {"caller_nid": "ctem_demo_004_e2e_main", "callee": "print", "source_file": "scripts/ctem_demo_004_e2e.py", "source_location": "L711"}, {"caller_nid": "ctem_demo_004_e2e_main", "callee": "print", "source_file": "scripts/ctem_demo_004_e2e.py", "source_location": "L712"}, {"caller_nid": "ctem_demo_004_e2e_main", "callee": "print", "source_file": "scripts/ctem_demo_004_e2e.py", "source_location": "L713"}, {"caller_nid": "ctem_demo_004_e2e_main", "callee": "print", "source_file": "scripts/ctem_demo_004_e2e.py", "source_location": "L714"}, {"caller_nid": "ctem_demo_004_e2e_main", "callee": "print", "source_file": "scripts/ctem_demo_004_e2e.py", "source_location": "L715"}, {"caller_nid": "ctem_demo_004_e2e_main", "callee": "print", "source_file": "scripts/ctem_demo_004_e2e.py", "source_location": "L716"}, {"caller_nid": "ctem_demo_004_e2e_main", "callee": "print", "source_file": "scripts/ctem_demo_004_e2e.py", "source_location": "L717"}, {"caller_nid": "ctem_demo_004_e2e_main", "callee": "print", "source_file": "scripts/ctem_demo_004_e2e.py", "source_location": "L718"}, {"caller_nid": "ctem_demo_004_e2e_main", "callee": "makedirs", "source_file": "scripts/ctem_demo_004_e2e.py", "source_location": "L721"}, {"caller_nid": "ctem_demo_004_e2e_main", "callee": "strftime", "source_file": "scripts/ctem_demo_004_e2e.py", "source_location": "L722"}, {"caller_nid": "ctem_demo_004_e2e_main", "callee": "now", "source_file": "scripts/ctem_demo_004_e2e.py", "source_location": "L722"}, {"caller_nid": "ctem_demo_004_e2e_main", "callee": "open", "source_file": "scripts/ctem_demo_004_e2e.py", "source_location": "L724"}, {"caller_nid": "ctem_demo_004_e2e_main", "callee": "dump", "source_file": "scripts/ctem_demo_004_e2e.py", "source_location": "L725"}, {"caller_nid": "ctem_demo_004_e2e_main", "callee": "isoformat", "source_file": "scripts/ctem_demo_004_e2e.py", "source_location": "L727"}, {"caller_nid": "ctem_demo_004_e2e_main", "callee": "now", "source_file": "scripts/ctem_demo_004_e2e.py", "source_location": "L727"}, {"caller_nid": "ctem_demo_004_e2e_main", "callee": "round", "source_file": "scripts/ctem_demo_004_e2e.py", "source_location": "L729"}, {"caller_nid": "ctem_demo_004_e2e_main", "callee": "print", "source_file": "scripts/ctem_demo_004_e2e.py", "source_location": "L732"}, {"caller_nid": "ctem_demo_004_e2e_main", "callee": "exit", "source_file": "scripts/ctem_demo_004_e2e.py", "source_location": "L734"}]}